Magphi/__init__.py
Magphi/__main__.py
Magphi/check_depencies.py
Magphi/check_inputs.py
Magphi/commandline_interface.py
Magphi/exit_with_error.py
Magphi/search_insertion_sites.py
Magphi/seed_handling.py
Magphi/split_gff_file.py
Magphi/wrangle_outputs.py
Magphi/write_output_csv.py
Magphi-2.0.2.dist-info/LICENSE
Magphi-2.0.2.dist-info/METADATA
Magphi-2.0.2.dist-info/WHEEL
Magphi-2.0.2.dist-info/entry_points.txt
Magphi-2.0.2.dist-info/top_level.txt
Magphi-2.0.2.dist-info/RECORD
