Metadata-Version: 2.1
Name: Magphi
Version: 2.0.2
Summary: A bioinformatics tool allowing for examnination and extraction of genomic features using seed sequences.
Home-page: https://github.com/milnus/Magphi
Author: Magnus Ganer Jespersen
Author-email: magnus.ganer.j@gmail.com
License: MIT license
Keywords: Genomic,extraction,bacteria,prokaryotes,bioinformatics
Classifier: Programming Language :: Python :: 3.9
Classifier: License :: OSI Approved :: MIT License
Classifier: Operating System :: OS Independent
Classifier: Intended Audience :: Science/Research
Classifier: Topic :: Scientific/Engineering :: Bio-Informatics
Classifier: Development Status :: 4 - Beta
License-File: LICENSE
Requires-Dist: biopython (>=1.79)
Requires-Dist: pybedtools (==0.8.2)
